[
  {
    "id": 11895,
    "date": "30/06/2020",
    "value": "-185.57",
    "cost_center_id": 23,
    "congressman_budget_id": 1059,
    "object": "COMBUSTIVEL",
    "to": "SEVES",
    "entry_type_id": 5,
    "document_number": "41636",
    "provider_id": 316,
    "verified_at": "2020-09-23 15:25:03",
    "verified_by_id": 45,
    "analysed_at": "2020-10-28 23:06:10",
    "analysed_by_id": 77,
    "published_at": "2020-11-06 12:49:12",
    "published_by_id": 77,
    "created_at": "2020-09-23 15:24:55",
    "created_by_id": 45,
    "updated_at": "2020-11-06 12:49:12",
    "updated_by_id": 77,
    "cost_center_name": "Combustíveis e lubrificantes",
    "cost_center_code": "VII",
    "provider_name": "SEVES POSTO DE SERVIÇOS LTDA",
    "provider_cpf_cnpj": "27.109.255/0001-43",
    "provider_type": "CNPJ",
    "entry_type_name": "Débito",
    "provider_is_blocked": false,
    "documents_count": 1,
    "missing_verification": false,
    "missing_analysis": false,
    "is_transport_or_credit": false,
    "comments_count": 0,
    "date_formatted": "30/06/2020",
    "value_formatted": "R$ -185,57",
    "value_abs": 185.57,
    "cost_center_name_formatted": "Combustíveis e lubrificantes",
    "name": "SEVES POSTO DE SERVIÇOS LTDA",
    "cpf_cnpj": "CNPJ: 27.109.255/0001-43",
    "pendencies": [

    ]
  },
  {
    "id": 13237,
    "date": "30/06/2020",
    "value": "-15754.82",
    "cost_center_id": 26,
    "congressman_budget_id": 1059,
    "object": "DEVOLUÇÃO DE SALDO ACUMULADO NO PRIMEIRO SEMESTRE DE 2020",
    "to": "Assembleia Legislativa do Estado do Rio de Janeiro",
    "entry_type_id": 3,
    "document_number": null,
    "provider_id": 1,
    "verified_at": "2020-11-17 15:22:38",
    "verified_by_id": 45,
    "analysed_at": "2020-11-17 15:22:50",
    "analysed_by_id": 77,
    "published_at": "2020-11-17 15:22:53",
    "published_by_id": 77,
    "created_at": "2020-11-17 15:22:30",
    "created_by_id": 45,
    "updated_at": "2020-11-17 15:22:53",
    "updated_by_id": 77,
    "cost_center_name": "Devolução de saldo",
    "cost_center_code": "4",
    "provider_name": "Assembleia Legislativa do Estado do Rio de Janeiro",
    "provider_cpf_cnpj": "30.449.862/0001-67",
    "provider_type": "PJ",
    "entry_type_name": "Transferência",
    "provider_is_blocked": false,
    "documents_count": 0,
    "missing_verification": false,
    "missing_analysis": false,
    "is_transport_or_credit": false,
    "comments_count": 0,
    "date_formatted": "30/06/2020",
    "value_formatted": "R$ -15.754,82",
    "value_abs": 15754.82,
    "cost_center_name_formatted": "Devolução de saldo",
    "name": "Assembleia Legislativa do Estado do Rio de Janeiro",
    "cpf_cnpj": "PJ: 30.449.862/0001-67",
    "pendencies": [

    ]
  },
  {
    "id": 11948,
    "date": "22/06/2020",
    "value": "-185.00",
    "cost_center_id": 12,
    "congressman_budget_id": 1059,
    "object": "LOCAÇÃO COMPUTADORES",
    "to": "LOGICA TECNOLOGIA - EIRELI EPP",
    "entry_type_id": 5,
    "document_number": "LG09841",
    "provider_id": 107,
    "verified_at": "2020-11-04 19:04:28",
    "verified_by_id": 45,
    "analysed_at": "2020-11-06 12:46:56",
    "analysed_by_id": 77,
    "published_at": "2020-11-06 12:46:59",
    "published_by_id": 77,
    "created_at": "2020-09-24 17:18:12",
    "created_by_id": 45,
    "updated_at": "2020-11-06 12:46:59",
    "updated_by_id": 77,
    "cost_center_name": "Locação de móveis e equipamentos",
    "cost_center_code": "IV.a",
    "provider_name": "LOGICA TECNOLOGIA - EIRELI EPP",
    "provider_cpf_cnpj": "03.817.776/0001-97",
    "provider_type": "CNPJ",
    "entry_type_name": "Débito",
    "provider_is_blocked": false,
    "documents_count": 1,
    "missing_verification": false,
    "missing_analysis": false,
    "is_transport_or_credit": false,
    "comments_count": 0,
    "date_formatted": "22/06/2020",
    "value_formatted": "R$ -185,00",
    "value_abs": 185,
    "cost_center_name_formatted": "Locação de móveis e equipamentos",
    "name": "LOGICA TECNOLOGIA - EIRELI EPP",
    "cpf_cnpj": "CNPJ: 03.817.776/0001-97",
    "pendencies": [

    ]
  },
  {
    "id": 11947,
    "date": "22/06/2020",
    "value": "-185.00",
    "cost_center_id": 12,
    "congressman_budget_id": 1059,
    "object": "LOCAÇÃO COMPUTADORES",
    "to": "LOGICA TECNOLOGIA - EIRELI EPP",
    "entry_type_id": 5,
    "document_number": "LG009859",
    "provider_id": 107,
    "verified_at": "2020-10-27 12:41:01",
    "verified_by_id": 45,
    "analysed_at": "2020-10-28 22:57:42",
    "analysed_by_id": 77,
    "published_at": "2020-11-06 12:37:51",
    "published_by_id": 77,
    "created_at": "2020-09-24 17:16:23",
    "created_by_id": 45,
    "updated_at": "2020-11-06 12:37:51",
    "updated_by_id": 77,
    "cost_center_name": "Locação de móveis e equipamentos",
    "cost_center_code": "IV.a",
    "provider_name": "LOGICA TECNOLOGIA - EIRELI EPP",
    "provider_cpf_cnpj": "03.817.776/0001-97",
    "provider_type": "CNPJ",
    "entry_type_name": "Débito",
    "provider_is_blocked": false,
    "documents_count": 1,
    "missing_verification": false,
    "missing_analysis": false,
    "is_transport_or_credit": false,
    "comments_count": 0,
    "date_formatted": "22/06/2020",
    "value_formatted": "R$ -185,00",
    "value_abs": 185,
    "cost_center_name_formatted": "Locação de móveis e equipamentos",
    "name": "LOGICA TECNOLOGIA - EIRELI EPP",
    "cpf_cnpj": "CNPJ: 03.817.776/0001-97",
    "pendencies": [

    ]
  },
  {
    "id": 11371,
    "date": "18/06/2020",
    "value": "-150.08",
    "cost_center_id": 23,
    "congressman_budget_id": 1059,
    "object": "COMBUSTÍVEL",
    "to": "GERECINO AUTO POSTO",
    "entry_type_id": 5,
    "document_number": "944420",
    "provider_id": 319,
    "verified_at": "2020-09-01 13:29:13",
    "verified_by_id": 45,
    "analysed_at": "2020-11-06 12:35:53",
    "analysed_by_id": 77,
    "published_at": "2020-11-06 12:35:57",
    "published_by_id": 77,
    "created_at": "2020-09-01 13:14:44",
    "created_by_id": 45,
    "updated_at": "2020-11-06 12:35:57",
    "updated_by_id": 77,
    "cost_center_name": "Combustíveis e lubrificantes",
    "cost_center_code": "VII",
    "provider_name": "GERECINO AUTO POSTO",
    "provider_cpf_cnpj": "42.309.849/0001-91",
    "provider_type": "CNPJ",
    "entry_type_name": "Débito",
    "provider_is_blocked": false,
    "documents_count": 1,
    "missing_verification": false,
    "missing_analysis": false,
    "is_transport_or_credit": false,
    "comments_count": 0,
    "date_formatted": "18/06/2020",
    "value_formatted": "R$ -150,08",
    "value_abs": 150.08,
    "cost_center_name_formatted": "Combustíveis e lubrificantes",
    "name": "GERECINO AUTO POSTO",
    "cpf_cnpj": "CNPJ: 42.309.849/0001-91",
    "pendencies": [

    ]
  },
  {
    "id": 11370,
    "date": "18/06/2020",
    "value": "-146.78",
    "cost_center_id": 23,
    "congressman_budget_id": 1059,
    "object": "COMBUSTÍVEL",
    "to": "POSTO DE GASOLINA MARECHAL DE BANGU",
    "entry_type_id": 5,
    "document_number": "146,78",
    "provider_id": 518,
    "verified_at": "2020-09-01 13:29:15",
    "verified_by_id": 45,
    "analysed_at": "2020-10-28 22:26:16",
    "analysed_by_id": 77,
    "published_at": "2020-11-06 12:35:47",
    "published_by_id": 77,
    "created_at": "2020-09-01 13:10:37",
    "created_by_id": 45,
    "updated_at": "2020-11-06 12:35:47",
    "updated_by_id": 77,
    "cost_center_name": "Combustíveis e lubrificantes",
    "cost_center_code": "VII",
    "provider_name": "POSTO DE GASOLINA MARECHAL DE BANGU",
    "provider_cpf_cnpj": "02.553.357/0001-22",
    "provider_type": "CNPJ",
    "entry_type_name": "Débito",
    "provider_is_blocked": false,
    "documents_count": 1,
    "missing_verification": false,
    "missing_analysis": false,
    "is_transport_or_credit": false,
    "comments_count": 0,
    "date_formatted": "18/06/2020",
    "value_formatted": "R$ -146,78",
    "value_abs": 146.78,
    "cost_center_name_formatted": "Combustíveis e lubrificantes",
    "name": "POSTO DE GASOLINA MARECHAL DE BANGU",
    "cpf_cnpj": "CNPJ: 02.553.357/0001-22",
    "pendencies": [

    ]
  },
  {
    "id": 11946,
    "date": "16/06/2020",
    "value": "-350.00",
    "cost_center_id": 12,
    "congressman_budget_id": 1059,
    "object": "LOCAÇÃO COMPUTADORES",
    "to": "LOGICA TECNOLOGIA - EIRELI EPP",
    "entry_type_id": 5,
    "document_number": "LG009778",
    "provider_id": 107,
    "verified_at": "2020-10-27 12:46:46",
    "verified_by_id": 45,
    "analysed_at": "2020-10-28 22:20:00",
    "analysed_by_id": 77,
    "published_at": "2020-11-06 12:35:21",
    "published_by_id": 77,
    "created_at": "2020-09-24 17:13:11",
    "created_by_id": 45,
    "updated_at": "2020-11-06 12:35:21",
    "updated_by_id": 77,
    "cost_center_name": "Locação de móveis e equipamentos",
    "cost_center_code": "IV.a",
    "provider_name": "LOGICA TECNOLOGIA - EIRELI EPP",
    "provider_cpf_cnpj": "03.817.776/0001-97",
    "provider_type": "CNPJ",
    "entry_type_name": "Débito",
    "provider_is_blocked": false,
    "documents_count": 1,
    "missing_verification": false,
    "missing_analysis": false,
    "is_transport_or_credit": false,
    "comments_count": 0,
    "date_formatted": "16/06/2020",
    "value_formatted": "R$ -350,00",
    "value_abs": 350,
    "cost_center_name_formatted": "Locação de móveis e equipamentos",
    "name": "LOGICA TECNOLOGIA - EIRELI EPP",
    "cpf_cnpj": "CNPJ: 03.817.776/0001-97",
    "pendencies": [

    ]
  },
  {
    "id": 11369,
    "date": "12/06/2020",
    "value": "-220.20",
    "cost_center_id": 23,
    "congressman_budget_id": 1059,
    "object": "COMBUSTÍVEL",
    "to": "POSTO DE GASOLINA BOA FÉ LTDA",
    "entry_type_id": 4,
    "document_number": "0020",
    "provider_id": 178,
    "verified_at": "2020-10-20 14:58:32",
    "verified_by_id": 45,
    "analysed_at": "2020-10-28 22:02:58",
    "analysed_by_id": 77,
    "published_at": "2020-11-06 12:35:24",
    "published_by_id": 77,
    "created_at": "2020-09-01 12:51:20",
    "created_by_id": 45,
    "updated_at": "2020-11-06 12:35:24",
    "updated_by_id": 77,
    "cost_center_name": "Combustíveis e lubrificantes",
    "cost_center_code": "VII",
    "provider_name": "POSTO DE GASOLINA BOA FÉ LTDA",
    "provider_cpf_cnpj": "34.087.908/0001-04",
    "provider_type": "CNPJ",
    "entry_type_name": "Cheque",
    "provider_is_blocked": false,
    "documents_count": 1,
    "missing_verification": false,
    "missing_analysis": false,
    "is_transport_or_credit": false,
    "comments_count": 0,
    "date_formatted": "12/06/2020",
    "value_formatted": "R$ -220,20",
    "value_abs": 220.2,
    "cost_center_name_formatted": "Combustíveis e lubrificantes",
    "name": "POSTO DE GASOLINA BOA FÉ LTDA",
    "cpf_cnpj": "CNPJ: 34.087.908/0001-04",
    "pendencies": [

    ]
  },
  {
    "id": 12583,
    "date": "10/06/2020",
    "value": "-1980.38",
    "cost_center_id": 21,
    "congressman_budget_id": 1059,
    "object": "LOCAÇÃO AUTOMÓVEL",
    "to": "Localiza Rent a Car S.A",
    "entry_type_id": 5,
    "document_number": "842714",
    "provider_id": 431,
    "verified_at": "2020-10-16 16:14:53",
    "verified_by_id": 45,
    "analysed_at": "2020-10-28 22:02:35",
    "analysed_by_id": 77,
    "published_at": "2020-11-06 12:34:08",
    "published_by_id": 77,
    "created_at": "2020-10-16 16:14:30",
    "created_by_id": 45,
    "updated_at": "2020-11-06 12:34:08",
    "updated_by_id": 77,
    "cost_center_name": "Locação ou fretamento de veículos automotores",
    "cost_center_code": "VI.a",
    "provider_name": "Localiza Rent a Car S.A",
    "provider_cpf_cnpj": "16.670.085/0044-95",
    "provider_type": "CNPJ",
    "entry_type_name": "Débito",
    "provider_is_blocked": false,
    "documents_count": 1,
    "missing_verification": false,
    "missing_analysis": false,
    "is_transport_or_credit": false,
    "comments_count": 0,
    "date_formatted": "10/06/2020",
    "value_formatted": "R$ -1.980,38",
    "value_abs": 1980.38,
    "cost_center_name_formatted": "Locação ou fretamento de veículos automotores",
    "name": "Localiza Rent a Car S.A",
    "cpf_cnpj": "CNPJ: 16.670.085/0044-95",
    "pendencies": [

    ]
  },
  {
    "id": 11950,
    "date": "10/06/2020",
    "value": "-26.50",
    "cost_center_id": 22,
    "congressman_budget_id": 1059,
    "object": "PEDÁGIO",
    "to": "CGMP CENTRO DE GESTAO DE MEIOS DE PAGAMENTO LTDA",
    "entry_type_id": 5,
    "document_number": "2077371280",
    "provider_id": 11,
    "verified_at": "2020-11-09 14:09:33",
    "verified_by_id": 45,
    "analysed_at": "2020-11-09 14:56:57",
    "analysed_by_id": 77,
    "published_at": "2020-11-09 14:57:02",
    "published_by_id": 77,
    "created_at": "2020-09-24 17:32:00",
    "created_by_id": 45,
    "updated_at": "2020-11-09 14:57:02",
    "updated_by_id": 77,
    "cost_center_name": "Serviços de táxi, STIP, transportes públicos, pedágio e estacionamento",
    "cost_center_code": "VI.b",
    "provider_name": "CGMP CENTRO DE GESTAO DE MEIOS DE PAGAMENTO LTDA",
    "provider_cpf_cnpj": "04.088.208/0001-65",
    "provider_type": "CNPJ",
    "entry_type_name": "Débito",
    "provider_is_blocked": false,
    "documents_count": 1,
    "missing_verification": false,
    "missing_analysis": false,
    "is_transport_or_credit": false,
    "comments_count": 0,
    "date_formatted": "10/06/2020",
    "value_formatted": "R$ -26,50",
    "value_abs": 26.5,
    "cost_center_name_formatted": "Serviços de táxi, STIP, transportes públicos, pedágio e esta...",
    "name": "CGMP CENTRO DE GESTAO DE MEIOS DE PAGAMENTO LTDA",
    "cpf_cnpj": "CNPJ: 04.088.208/0001-65",
    "pendencies": [

    ]
  },
  {
    "id": 11373,
    "date": "01/06/2020",
    "value": "-10.00",
    "cost_center_id": 28,
    "congressman_budget_id": 1059,
    "object": "TARIFA",
    "to": "ITAU UNIBANCO S.A.",
    "entry_type_id": 5,
    "document_number": "0106",
    "provider_id": 276,
    "verified_at": "2020-09-01 13:35:48",
    "verified_by_id": 45,
    "analysed_at": "2020-10-19 21:30:21",
    "analysed_by_id": 77,
    "published_at": "2020-11-06 12:00:15",
    "published_by_id": 77,
    "created_at": "2020-09-01 13:35:42",
    "created_by_id": 45,
    "updated_at": "2020-11-06 12:00:15",
    "updated_by_id": 77,
    "cost_center_name": "Tarifas bancárias da conta corrente",
    "cost_center_code": "XI",
    "provider_name": "ITAU UNIBANCO S.A.",
    "provider_cpf_cnpj": "60.701.190/0001-04",
    "provider_type": "PJ",
    "entry_type_name": "Débito",
    "provider_is_blocked": false,
    "documents_count": 0,
    "missing_verification": false,
    "missing_analysis": false,
    "is_transport_or_credit": false,
    "comments_count": 0,
    "date_formatted": "01/06/2020",
    "value_formatted": "R$ -10,00",
    "value_abs": 10,
    "cost_center_name_formatted": "Tarifas bancárias da conta corrente",
    "name": "ITAU UNIBANCO S.A.",
    "cpf_cnpj": "PJ: 60.701.190/0001-04",
    "pendencies": [

    ]
  }
]