[
  {
    "id": 11806,
    "date": "31/07/2020",
    "value": "-198.65",
    "cost_center_id": 23,
    "congressman_budget_id": 1138,
    "object": "combustível",
    "to": "VENTURA COMERCIO E SERVIÇOS LTDA",
    "entry_type_id": 6,
    "document_number": null,
    "provider_id": 30,
    "verified_at": "2020-09-17 18:21:23",
    "verified_by_id": 50,
    "analysed_at": "2020-09-17 19:44:06",
    "analysed_by_id": 77,
    "published_at": "2020-11-04 16:05:17",
    "published_by_id": 77,
    "created_at": "2020-09-17 18:19:23",
    "created_by_id": 50,
    "updated_at": "2020-11-04 16:05:17",
    "updated_by_id": 77,
    "cost_center_name": "Combustíveis e lubrificantes",
    "cost_center_code": "VII",
    "provider_name": "VENTURA COMERCIO E SERVIÇOS LTDA",
    "provider_cpf_cnpj": "02.083.719/0001-69",
    "provider_type": "CNPJ",
    "entry_type_name": "Débito em conta",
    "provider_is_blocked": false,
    "documents_count": 1,
    "missing_verification": false,
    "missing_analysis": false,
    "is_transport_or_credit": false,
    "comments_count": 0,
    "date_formatted": "31/07/2020",
    "value_formatted": "R$ -198,65",
    "value_abs": 198.65,
    "cost_center_name_formatted": "Combustíveis e lubrificantes",
    "name": "VENTURA COMERCIO E SERVIÇOS LTDA",
    "cpf_cnpj": "CNPJ: 02.083.719/0001-69",
    "pendencies": [

    ]
  },
  {
    "id": 10674,
    "date": "31/07/2020",
    "value": "-3869.52",
    "cost_center_id": 7,
    "congressman_budget_id": 1138,
    "object": "ALUGUEL DO IMÓVEL",
    "to": "VIVALDO GOMES DE AGUIAR",
    "entry_type_id": 3,
    "document_number": null,
    "provider_id": 137,
    "verified_at": "2020-09-03 14:56:34",
    "verified_by_id": 50,
    "analysed_at": "2020-09-17 19:33:16",
    "analysed_by_id": 77,
    "published_at": "2020-11-04 16:05:14",
    "published_by_id": 77,
    "created_at": "2020-08-04 15:24:18",
    "created_by_id": 50,
    "updated_at": "2020-11-04 16:05:14",
    "updated_by_id": 77,
    "cost_center_name": "Locação de imóveis",
    "cost_center_code": "III.a",
    "provider_name": "VIVALDO GOMES DE AGUIAR",
    "provider_cpf_cnpj": "094.740.997-15",
    "provider_type": "CPF",
    "entry_type_name": "Transferência",
    "provider_is_blocked": false,
    "documents_count": 1,
    "missing_verification": false,
    "missing_analysis": false,
    "is_transport_or_credit": false,
    "comments_count": 0,
    "date_formatted": "31/07/2020",
    "value_formatted": "R$ -3.869,52",
    "value_abs": 3869.52,
    "cost_center_name_formatted": "Locação de imóveis",
    "name": "VIVALDO GOMES DE AGUIAR",
    "cpf_cnpj": "CPF: 094.740.997-15",
    "pendencies": [

    ]
  },
  {
    "id": 10673,
    "date": "31/07/2020",
    "value": "-7450.00",
    "cost_center_id": 21,
    "congressman_budget_id": 1138,
    "object": "ALUGUEL DO CARRO",
    "to": "LJS EMPREENDIMENTOS E PARTICIPAÇÕES EIRELI",
    "entry_type_id": 5,
    "document_number": null,
    "provider_id": 90,
    "verified_at": "2020-09-08 18:29:38",
    "verified_by_id": 50,
    "analysed_at": "2020-09-17 19:29:02",
    "analysed_by_id": 77,
    "published_at": "2020-11-04 16:05:10",
    "published_by_id": 77,
    "created_at": "2020-08-04 15:20:02",
    "created_by_id": 50,
    "updated_at": "2020-11-04 16:05:10",
    "updated_by_id": 77,
    "cost_center_name": "Locação ou fretamento de veículos automotores",
    "cost_center_code": "VI.a",
    "provider_name": "LJS EMPREENDIMENTOS E PARTICIPAÇÕES EIRELI",
    "provider_cpf_cnpj": "26.237.310/0001-18",
    "provider_type": "CNPJ",
    "entry_type_name": "Débito",
    "provider_is_blocked": false,
    "documents_count": 1,
    "missing_verification": false,
    "missing_analysis": false,
    "is_transport_or_credit": false,
    "comments_count": 0,
    "date_formatted": "31/07/2020",
    "value_formatted": "R$ -7.450,00",
    "value_abs": 7450,
    "cost_center_name_formatted": "Locação ou fretamento de veículos automotores",
    "name": "LJS EMPREENDIMENTOS E PARTICIPAÇÕES EIRELI",
    "cpf_cnpj": "CNPJ: 26.237.310/0001-18",
    "pendencies": [

    ]
  },
  {
    "id": 12412,
    "date": "31/07/2020",
    "value": "-1597.13",
    "cost_center_id": 23,
    "congressman_budget_id": 1138,
    "object": "combustível",
    "to": "ENZO QUEIMADOS LTDS",
    "entry_type_id": 4,
    "document_number": "093",
    "provider_id": 181,
    "verified_at": "2020-10-07 16:10:38",
    "verified_by_id": 50,
    "analysed_at": "2020-11-04 15:24:27",
    "analysed_by_id": 77,
    "published_at": "2020-11-04 16:05:07",
    "published_by_id": 77,
    "created_at": "2020-10-07 14:51:59",
    "created_by_id": 50,
    "updated_at": "2020-11-04 16:05:07",
    "updated_by_id": 77,
    "cost_center_name": "Combustíveis e lubrificantes",
    "cost_center_code": "VII",
    "provider_name": "ENZO QUEIMADOS LTDS",
    "provider_cpf_cnpj": "20.674.619/0001-99",
    "provider_type": "CNPJ",
    "entry_type_name": "Cheque",
    "provider_is_blocked": false,
    "documents_count": 2,
    "missing_verification": false,
    "missing_analysis": false,
    "is_transport_or_credit": false,
    "comments_count": 0,
    "date_formatted": "31/07/2020",
    "value_formatted": "R$ -1.597,13",
    "value_abs": 1597.13,
    "cost_center_name_formatted": "Combustíveis e lubrificantes",
    "name": "ENZO QUEIMADOS LTDS",
    "cpf_cnpj": "CNPJ: 20.674.619/0001-99",
    "pendencies": [

    ]
  },
  {
    "id": 14034,
    "date": "31/07/2020",
    "value": "-112.05",
    "cost_center_id": 14,
    "congressman_budget_id": 1138,
    "object": "tim",
    "to": "TIM S.A",
    "entry_type_id": 6,
    "document_number": null,
    "provider_id": 385,
    "verified_at": "2020-12-08 13:03:33",
    "verified_by_id": 50,
    "analysed_at": "2020-12-10 20:01:53",
    "analysed_by_id": 77,
    "published_at": "2020-12-10 20:01:58",
    "published_by_id": 77,
    "created_at": "2020-12-08 12:59:21",
    "created_by_id": 50,
    "updated_at": "2020-12-10 20:01:58",
    "updated_by_id": 77,
    "cost_center_name": "Acesso à internet",
    "cost_center_code": "IV.c",
    "provider_name": "TIM S.A",
    "provider_cpf_cnpj": "02.421.421/0001-11",
    "provider_type": "CNPJ",
    "entry_type_name": "Débito em conta",
    "provider_is_blocked": false,
    "documents_count": 1,
    "missing_verification": false,
    "missing_analysis": false,
    "is_transport_or_credit": false,
    "comments_count": 0,
    "date_formatted": "31/07/2020",
    "value_formatted": "R$ -112,05",
    "value_abs": 112.05,
    "cost_center_name_formatted": "Acesso à internet",
    "name": "TIM S.A",
    "cpf_cnpj": "CNPJ: 02.421.421/0001-11",
    "pendencies": [

    ]
  },
  {
    "id": 10676,
    "date": "29/07/2020",
    "value": "-172.09",
    "cost_center_id": 23,
    "congressman_budget_id": 1138,
    "object": "combustível",
    "to": "Auto posto de serviços shopping Madureira 01",
    "entry_type_id": 5,
    "document_number": null,
    "provider_id": 171,
    "verified_at": "2020-09-03 15:12:33",
    "verified_by_id": 50,
    "analysed_at": "2020-09-24 23:53:31",
    "analysed_by_id": 77,
    "published_at": "2020-11-04 16:05:03",
    "published_by_id": 77,
    "created_at": "2020-08-04 16:10:13",
    "created_by_id": 50,
    "updated_at": "2020-11-04 16:05:03",
    "updated_by_id": 77,
    "cost_center_name": "Combustíveis e lubrificantes",
    "cost_center_code": "VII",
    "provider_name": "Auto posto de serviços shopping Madureira 01",
    "provider_cpf_cnpj": "36.538.973/0001-26",
    "provider_type": "CNPJ",
    "entry_type_name": "Débito",
    "provider_is_blocked": false,
    "documents_count": 1,
    "missing_verification": false,
    "missing_analysis": false,
    "is_transport_or_credit": false,
    "comments_count": 0,
    "date_formatted": "29/07/2020",
    "value_formatted": "R$ -172,09",
    "value_abs": 172.09,
    "cost_center_name_formatted": "Combustíveis e lubrificantes",
    "name": "Auto posto de serviços shopping Madureira 01",
    "cpf_cnpj": "CNPJ: 36.538.973/0001-26",
    "pendencies": [

    ]
  },
  {
    "id": 10687,
    "date": "21/07/2020",
    "value": "-273.45",
    "cost_center_id": 23,
    "congressman_budget_id": 1138,
    "object": "combustível",
    "to": "AUTO POSTO SENNA LTDA",
    "entry_type_id": 6,
    "document_number": null,
    "provider_id": 235,
    "verified_at": "2020-09-03 15:02:46",
    "verified_by_id": 50,
    "analysed_at": "2020-11-04 15:11:42",
    "analysed_by_id": 77,
    "published_at": "2020-11-04 16:05:01",
    "published_by_id": 77,
    "created_at": "2020-08-04 17:05:03",
    "created_by_id": 50,
    "updated_at": "2020-11-04 16:05:01",
    "updated_by_id": 77,
    "cost_center_name": "Combustíveis e lubrificantes",
    "cost_center_code": "VII",
    "provider_name": "AUTO POSTO SENNA LTDA",
    "provider_cpf_cnpj": "02.575.190/0001-09",
    "provider_type": "CNPJ",
    "entry_type_name": "Débito em conta",
    "provider_is_blocked": false,
    "documents_count": 1,
    "missing_verification": false,
    "missing_analysis": false,
    "is_transport_or_credit": false,
    "comments_count": 0,
    "date_formatted": "21/07/2020",
    "value_formatted": "R$ -273,45",
    "value_abs": 273.45,
    "cost_center_name_formatted": "Combustíveis e lubrificantes",
    "name": "AUTO POSTO SENNA LTDA",
    "cpf_cnpj": "CNPJ: 02.575.190/0001-09",
    "pendencies": [

    ]
  },
  {
    "id": 10841,
    "date": "21/07/2020",
    "value": "-1450.00",
    "cost_center_id": 21,
    "congressman_budget_id": 1138,
    "object": "LOCAÇÃO DE VEÍCULO",
    "to": "FREEWAY TRANSPORTES EIRELE",
    "entry_type_id": 3,
    "document_number": null,
    "provider_id": 480,
    "verified_at": "2020-09-19 10:04:49",
    "verified_by_id": 50,
    "analysed_at": "2020-09-24 23:48:52",
    "analysed_by_id": 77,
    "published_at": "2020-11-04 16:04:54",
    "published_by_id": 77,
    "created_at": "2020-08-12 14:48:06",
    "created_by_id": 50,
    "updated_at": "2020-11-04 16:04:54",
    "updated_by_id": 77,
    "cost_center_name": "Locação ou fretamento de veículos automotores",
    "cost_center_code": "VI.a",
    "provider_name": "FREEWAY TRANSPORTES EIRELE",
    "provider_cpf_cnpj": "27.463.119/0001-57",
    "provider_type": "CNPJ",
    "entry_type_name": "Transferência",
    "provider_is_blocked": false,
    "documents_count": 1,
    "missing_verification": false,
    "missing_analysis": false,
    "is_transport_or_credit": false,
    "comments_count": 0,
    "date_formatted": "21/07/2020",
    "value_formatted": "R$ -1.450,00",
    "value_abs": 1450,
    "cost_center_name_formatted": "Locação ou fretamento de veículos automotores",
    "name": "FREEWAY TRANSPORTES EIRELE",
    "cpf_cnpj": "CNPJ: 27.463.119/0001-57",
    "pendencies": [

    ]
  },
  {
    "id": 11458,
    "date": "20/07/2020",
    "value": "-1368.51",
    "cost_center_id": 23,
    "congressman_budget_id": 1138,
    "object": "combustível",
    "to": "ENZO QUEIMADOS LTDS",
    "entry_type_id": 4,
    "document_number": "091",
    "provider_id": 181,
    "verified_at": "2020-09-15 15:10:51",
    "verified_by_id": 50,
    "analysed_at": "2020-09-17 19:10:29",
    "analysed_by_id": 77,
    "published_at": "2020-11-04 16:04:51",
    "published_by_id": 77,
    "created_at": "2020-09-03 16:27:04",
    "created_by_id": 50,
    "updated_at": "2020-11-04 16:04:51",
    "updated_by_id": 77,
    "cost_center_name": "Combustíveis e lubrificantes",
    "cost_center_code": "VII",
    "provider_name": "ENZO QUEIMADOS LTDS",
    "provider_cpf_cnpj": "20.674.619/0001-99",
    "provider_type": "CNPJ",
    "entry_type_name": "Cheque",
    "provider_is_blocked": false,
    "documents_count": 1,
    "missing_verification": false,
    "missing_analysis": false,
    "is_transport_or_credit": false,
    "comments_count": 0,
    "date_formatted": "20/07/2020",
    "value_formatted": "R$ -1.368,51",
    "value_abs": 1368.51,
    "cost_center_name_formatted": "Combustíveis e lubrificantes",
    "name": "ENZO QUEIMADOS LTDS",
    "cpf_cnpj": "CNPJ: 20.674.619/0001-99",
    "pendencies": [

    ]
  },
  {
    "id": 11455,
    "date": "19/07/2020",
    "value": "-1469.00",
    "cost_center_id": 12,
    "congressman_budget_id": 1138,
    "object": "aluguel dos móveis",
    "to": "ALUGARTE ALUGUEL DE MÓVEIS",
    "entry_type_id": 3,
    "document_number": null,
    "provider_id": 183,
    "verified_at": "2020-09-28 14:12:20",
    "verified_by_id": 50,
    "analysed_at": "2020-09-30 01:19:23",
    "analysed_by_id": 77,
    "published_at": "2020-11-04 16:04:49",
    "published_by_id": 77,
    "created_at": "2020-09-03 15:28:33",
    "created_by_id": 50,
    "updated_at": "2020-11-04 16:04:49",
    "updated_by_id": 77,
    "cost_center_name": "Locação de móveis e equipamentos",
    "cost_center_code": "IV.a",
    "provider_name": "ALUGARTE ALUGUEL DE MÓVEIS",
    "provider_cpf_cnpj": "15.538.900/0001-64",
    "provider_type": "CNPJ",
    "entry_type_name": "Transferência",
    "provider_is_blocked": false,
    "documents_count": 2,
    "missing_verification": false,
    "missing_analysis": false,
    "is_transport_or_credit": false,
    "comments_count": 0,
    "date_formatted": "19/07/2020",
    "value_formatted": "R$ -1.469,00",
    "value_abs": 1469,
    "cost_center_name_formatted": "Locação de móveis e equipamentos",
    "name": "ALUGARTE ALUGUEL DE MÓVEIS",
    "cpf_cnpj": "CNPJ: 15.538.900/0001-64",
    "pendencies": [

    ]
  },
  {
    "id": 10677,
    "date": "18/07/2020",
    "value": "-230.02",
    "cost_center_id": 23,
    "congressman_budget_id": 1138,
    "object": "combustível",
    "to": "AMIGAO DA DUTRA LTDA",
    "entry_type_id": 5,
    "document_number": null,
    "provider_id": 301,
    "verified_at": "2020-09-03 15:10:23",
    "verified_by_id": 50,
    "analysed_at": "2020-09-24 23:47:30",
    "analysed_by_id": 77,
    "published_at": "2020-11-04 16:04:47",
    "published_by_id": 77,
    "created_at": "2020-08-04 16:13:36",
    "created_by_id": 50,
    "updated_at": "2020-11-04 16:04:47",
    "updated_by_id": 77,
    "cost_center_name": "Combustíveis e lubrificantes",
    "cost_center_code": "VII",
    "provider_name": "POSTO DE GASOLINA AMIGÃO DA DUTRA LTDA.",
    "provider_cpf_cnpj": "40.233.686/0001-85",
    "provider_type": "PJ",
    "entry_type_name": "Débito",
    "provider_is_blocked": false,
    "documents_count": 1,
    "missing_verification": false,
    "missing_analysis": false,
    "is_transport_or_credit": false,
    "comments_count": 0,
    "date_formatted": "18/07/2020",
    "value_formatted": "R$ -230,02",
    "value_abs": 230.02,
    "cost_center_name_formatted": "Combustíveis e lubrificantes",
    "name": "POSTO DE GASOLINA AMIGÃO DA DUTRA LTDA.",
    "cpf_cnpj": "PJ: 40.233.686/0001-85",
    "pendencies": [

    ]
  },
  {
    "id": 10679,
    "date": "14/07/2020",
    "value": "-229.03",
    "cost_center_id": 23,
    "congressman_budget_id": 1138,
    "object": "combustível",
    "to": "AUTO POSTO MAQUINE LTDA",
    "entry_type_id": 6,
    "document_number": null,
    "provider_id": 254,
    "verified_at": "2020-09-03 15:07:03",
    "verified_by_id": 50,
    "analysed_at": "2020-09-17 18:50:02",
    "analysed_by_id": 77,
    "published_at": "2020-11-04 16:04:44",
    "published_by_id": 77,
    "created_at": "2020-08-04 16:47:30",
    "created_by_id": 50,
    "updated_at": "2020-11-04 16:04:44",
    "updated_by_id": 77,
    "cost_center_name": "Combustíveis e lubrificantes",
    "cost_center_code": "VII",
    "provider_name": "AUTO POSTO MAQUINE LTDA",
    "provider_cpf_cnpj": "42.357.715/0001-46",
    "provider_type": "CNPJ",
    "entry_type_name": "Débito em conta",
    "provider_is_blocked": false,
    "documents_count": 1,
    "missing_verification": false,
    "missing_analysis": false,
    "is_transport_or_credit": false,
    "comments_count": 0,
    "date_formatted": "14/07/2020",
    "value_formatted": "R$ -229,03",
    "value_abs": 229.03,
    "cost_center_name_formatted": "Combustíveis e lubrificantes",
    "name": "AUTO POSTO MAQUINE LTDA",
    "cpf_cnpj": "CNPJ: 42.357.715/0001-46",
    "pendencies": [

    ]
  },
  {
    "id": 10685,
    "date": "12/07/2020",
    "value": "-284.99",
    "cost_center_id": 23,
    "congressman_budget_id": 1138,
    "object": "combustível",
    "to": "AUTO POSTO PADDOCK CLUB",
    "entry_type_id": 6,
    "document_number": null,
    "provider_id": 767,
    "verified_at": "2020-09-03 15:03:59",
    "verified_by_id": 50,
    "analysed_at": "2020-11-04 15:11:08",
    "analysed_by_id": 77,
    "published_at": "2020-11-04 16:04:42",
    "published_by_id": 77,
    "created_at": "2020-08-04 17:00:33",
    "created_by_id": 50,
    "updated_at": "2020-11-04 16:04:42",
    "updated_by_id": 77,
    "cost_center_name": "Combustíveis e lubrificantes",
    "cost_center_code": "VII",
    "provider_name": "AUTO POSTO PADDOCK CLUB",
    "provider_cpf_cnpj": "13.179.099/0001-82",
    "provider_type": "CNPJ",
    "entry_type_name": "Débito em conta",
    "provider_is_blocked": false,
    "documents_count": 1,
    "missing_verification": false,
    "missing_analysis": false,
    "is_transport_or_credit": false,
    "comments_count": 0,
    "date_formatted": "12/07/2020",
    "value_formatted": "R$ -284,99",
    "value_abs": 284.99,
    "cost_center_name_formatted": "Combustíveis e lubrificantes",
    "name": "AUTO POSTO PADDOCK CLUB",
    "cpf_cnpj": "CNPJ: 13.179.099/0001-82",
    "pendencies": [

    ]
  },
  {
    "id": 10154,
    "date": "08/07/2020",
    "value": "-316.14",
    "cost_center_id": 10,
    "congressman_budget_id": 1138,
    "object": "light",
    "to": "light",
    "entry_type_id": 6,
    "document_number": null,
    "provider_id": 180,
    "verified_at": "2020-09-03 15:26:13",
    "verified_by_id": 50,
    "analysed_at": "2020-09-17 18:36:30",
    "analysed_by_id": 77,
    "published_at": "2020-11-04 16:04:38",
    "published_by_id": 77,
    "created_at": "2020-07-16 15:44:42",
    "created_by_id": 50,
    "updated_at": "2020-11-04 16:04:38",
    "updated_by_id": 77,
    "cost_center_name": "Serviços de energia elétrica, água e esgoto",
    "cost_center_code": "III.d",
    "provider_name": "light",
    "provider_cpf_cnpj": "60.444.437/0001-46",
    "provider_type": "CNPJ",
    "entry_type_name": "Débito em conta",
    "provider_is_blocked": false,
    "documents_count": 1,
    "missing_verification": false,
    "missing_analysis": false,
    "is_transport_or_credit": false,
    "comments_count": 0,
    "date_formatted": "08/07/2020",
    "value_formatted": "R$ -316,14",
    "value_abs": 316.14,
    "cost_center_name_formatted": "Serviços de energia elétrica, água e esgoto",
    "name": "light",
    "cpf_cnpj": "CNPJ: 60.444.437/0001-46",
    "pendencies": [

    ]
  },
  {
    "id": 10153,
    "date": "08/07/2020",
    "value": "-161.20",
    "cost_center_id": 10,
    "congressman_budget_id": 1138,
    "object": "light",
    "to": "light",
    "entry_type_id": 6,
    "document_number": null,
    "provider_id": 180,
    "verified_at": "2020-09-03 15:26:05",
    "verified_by_id": 50,
    "analysed_at": "2020-09-17 18:33:59",
    "analysed_by_id": 77,
    "published_at": "2020-11-04 16:04:33",
    "published_by_id": 77,
    "created_at": "2020-07-16 15:43:51",
    "created_by_id": 50,
    "updated_at": "2020-11-04 16:04:33",
    "updated_by_id": 77,
    "cost_center_name": "Serviços de energia elétrica, água e esgoto",
    "cost_center_code": "III.d",
    "provider_name": "light",
    "provider_cpf_cnpj": "60.444.437/0001-46",
    "provider_type": "CNPJ",
    "entry_type_name": "Débito em conta",
    "provider_is_blocked": false,
    "documents_count": 1,
    "missing_verification": false,
    "missing_analysis": false,
    "is_transport_or_credit": false,
    "comments_count": 0,
    "date_formatted": "08/07/2020",
    "value_formatted": "R$ -161,20",
    "value_abs": 161.2,
    "cost_center_name_formatted": "Serviços de energia elétrica, água e esgoto",
    "name": "light",
    "cpf_cnpj": "CNPJ: 60.444.437/0001-46",
    "pendencies": [

    ]
  },
  {
    "id": 10680,
    "date": "04/07/2020",
    "value": "-245.00",
    "cost_center_id": 23,
    "congressman_budget_id": 1138,
    "object": "combustível",
    "to": "POSTO SÃO CAETANO LTDA",
    "entry_type_id": 6,
    "document_number": null,
    "provider_id": 481,
    "verified_at": "2020-09-03 14:58:30",
    "verified_by_id": 50,
    "analysed_at": "2020-09-16 15:29:45",
    "analysed_by_id": 77,
    "published_at": "2020-11-04 16:04:26",
    "published_by_id": 77,
    "created_at": "2020-08-04 16:48:56",
    "created_by_id": 50,
    "updated_at": "2020-11-04 16:04:26",
    "updated_by_id": 77,
    "cost_center_name": "Combustíveis e lubrificantes",
    "cost_center_code": "VII",
    "provider_name": "POSTO SÃO CAETANO LTDA",
    "provider_cpf_cnpj": "30.807.929/0001-98",
    "provider_type": "CNPJ",
    "entry_type_name": "Débito em conta",
    "provider_is_blocked": false,
    "documents_count": 1,
    "missing_verification": false,
    "missing_analysis": false,
    "is_transport_or_credit": false,
    "comments_count": 0,
    "date_formatted": "04/07/2020",
    "value_formatted": "R$ -245,00",
    "value_abs": 245,
    "cost_center_name_formatted": "Combustíveis e lubrificantes",
    "name": "POSTO SÃO CAETANO LTDA",
    "cpf_cnpj": "CNPJ: 30.807.929/0001-98",
    "pendencies": [

    ]
  },
  {
    "id": 10682,
    "date": "02/07/2020",
    "value": "-242.95",
    "cost_center_id": 23,
    "congressman_budget_id": 1138,
    "object": "combustível",
    "to": "Auto posto de serviços shopping Madureira 01",
    "entry_type_id": 5,
    "document_number": null,
    "provider_id": 171,
    "verified_at": "2020-09-03 15:05:27",
    "verified_by_id": 50,
    "analysed_at": "2020-09-15 21:01:18",
    "analysed_by_id": 77,
    "published_at": "2020-11-04 16:04:24",
    "published_by_id": 77,
    "created_at": "2020-08-04 16:56:21",
    "created_by_id": 50,
    "updated_at": "2020-11-04 16:04:24",
    "updated_by_id": 77,
    "cost_center_name": "Combustíveis e lubrificantes",
    "cost_center_code": "VII",
    "provider_name": "Auto posto de serviços shopping Madureira 01",
    "provider_cpf_cnpj": "36.538.973/0001-26",
    "provider_type": "CNPJ",
    "entry_type_name": "Débito",
    "provider_is_blocked": false,
    "documents_count": 1,
    "missing_verification": false,
    "missing_analysis": false,
    "is_transport_or_credit": false,
    "comments_count": 0,
    "date_formatted": "02/07/2020",
    "value_formatted": "R$ -242,95",
    "value_abs": 242.95,
    "cost_center_name_formatted": "Combustíveis e lubrificantes",
    "name": "Auto posto de serviços shopping Madureira 01",
    "cpf_cnpj": "CNPJ: 36.538.973/0001-26",
    "pendencies": [

    ]
  },
  {
    "id": 11780,
    "date": "01/07/2020",
    "value": "-10.00",
    "cost_center_id": 28,
    "congressman_budget_id": 1138,
    "object": "tarifa cartão",
    "to": "ITAU UNIBANCO S.A.",
    "entry_type_id": 6,
    "document_number": null,
    "provider_id": 276,
    "verified_at": "2020-09-17 16:41:29",
    "verified_by_id": 50,
    "analysed_at": "2020-09-17 18:23:27",
    "analysed_by_id": 77,
    "published_at": "2020-11-04 16:04:20",
    "published_by_id": 77,
    "created_at": "2020-09-17 16:41:18",
    "created_by_id": 50,
    "updated_at": "2020-11-04 16:04:20",
    "updated_by_id": 77,
    "cost_center_name": "Tarifas bancárias da conta corrente",
    "cost_center_code": "XI",
    "provider_name": "ITAU UNIBANCO S.A.",
    "provider_cpf_cnpj": "60.701.190/0001-04",
    "provider_type": "PJ",
    "entry_type_name": "Débito em conta",
    "provider_is_blocked": false,
    "documents_count": 0,
    "missing_verification": false,
    "missing_analysis": false,
    "is_transport_or_credit": false,
    "comments_count": 0,
    "date_formatted": "01/07/2020",
    "value_formatted": "R$ -10,00",
    "value_abs": 10,
    "cost_center_name_formatted": "Tarifas bancárias da conta corrente",
    "name": "ITAU UNIBANCO S.A.",
    "cpf_cnpj": "PJ: 60.701.190/0001-04",
    "pendencies": [

    ]
  }
]