[
  {
    "id": 1580,
    "date": "30/09/2019",
    "value": "-5364.02",
    "cost_center_id": 23,
    "congressman_budget_id": 438,
    "object": "Combustível",
    "to": "Golden Green Auto Posto LTDA",
    "entry_type_id": 4,
    "document_number": "AA000037",
    "provider_id": 66,
    "verified_at": "2020-05-04 16:14:11",
    "verified_by_id": 61,
    "analysed_at": "2020-05-04 16:23:37",
    "analysed_by_id": 75,
    "published_at": "2020-05-04 16:23:42",
    "published_by_id": 75,
    "created_at": "2019-09-05 00:56:06",
    "created_by_id": 61,
    "updated_at": "2020-05-04 16:23:42",
    "updated_by_id": 75,
    "cost_center_name": "Combustíveis e lubrificantes",
    "cost_center_code": "VII",
    "provider_name": "Golden Green Auto Posto LTDA",
    "provider_cpf_cnpj": "02.373.202/0001-04",
    "provider_type": "CNPJ",
    "entry_type_name": "Cheque",
    "provider_is_blocked": false,
    "documents_count": 2,
    "missing_verification": false,
    "missing_analysis": false,
    "is_transport_or_credit": false,
    "comments_count": 0,
    "date_formatted": "30/09/2019",
    "value_formatted": "R$ -5.364,02",
    "value_abs": 5364.02,
    "cost_center_name_formatted": "Combustíveis e lubrificantes",
    "name": "Golden Green Auto Posto LTDA",
    "cpf_cnpj": "CNPJ: 02.373.202/0001-04",
    "pendencies": [

    ]
  },
  {
    "id": 2011,
    "date": "27/09/2019",
    "value": "-320.00",
    "cost_center_id": 13,
    "congressman_budget_id": 438,
    "object": "Suprimentos de informática",
    "to": "Fabio Thomaz Carneiro",
    "entry_type_id": 5,
    "document_number": null,
    "provider_id": 268,
    "verified_at": "2019-11-28 18:58:59",
    "verified_by_id": 61,
    "analysed_at": "2019-12-20 15:52:53",
    "analysed_by_id": 75,
    "published_at": "2019-12-20 15:52:56",
    "published_by_id": 75,
    "created_at": "2019-09-30 20:41:18",
    "created_by_id": 61,
    "updated_at": "2019-12-20 15:52:56",
    "updated_by_id": 75,
    "cost_center_name": "Material de expediente e suprimentos de informática",
    "cost_center_code": "IV.b",
    "provider_name": "Fabio Thomaz Carneiro",
    "provider_cpf_cnpj": "23.260.594/0001-75",
    "provider_type": "CNPJ",
    "entry_type_name": "Débito",
    "provider_is_blocked": false,
    "documents_count": 1,
    "missing_verification": false,
    "missing_analysis": false,
    "is_transport_or_credit": false,
    "comments_count": 0,
    "date_formatted": "27/09/2019",
    "value_formatted": "R$ -320,00",
    "value_abs": 320,
    "cost_center_name_formatted": "Material de expediente e suprimentos de informática",
    "name": "Fabio Thomaz Carneiro",
    "cpf_cnpj": "CNPJ: 23.260.594/0001-75",
    "pendencies": [

    ]
  },
  {
    "id": 3513,
    "date": "27/09/2019",
    "value": "-10.00",
    "cost_center_id": 28,
    "congressman_budget_id": 438,
    "object": "Tarifa bancária",
    "to": "BANCO ITAU",
    "entry_type_id": 6,
    "document_number": null,
    "provider_id": 276,
    "verified_at": "2019-11-28 18:20:40",
    "verified_by_id": 61,
    "analysed_at": "2019-12-20 15:52:59",
    "analysed_by_id": 75,
    "published_at": "2019-12-20 15:53:03",
    "published_by_id": 75,
    "created_at": "2019-11-28 18:18:40",
    "created_by_id": 61,
    "updated_at": "2019-12-20 15:53:03",
    "updated_by_id": 75,
    "cost_center_name": "Tarifas bancárias da conta corrente",
    "cost_center_code": "XI",
    "provider_name": "ITAU UNIBANCO S.A.",
    "provider_cpf_cnpj": "60.701.190/0001-04",
    "provider_type": "PJ",
    "entry_type_name": "Débito em conta",
    "provider_is_blocked": false,
    "documents_count": 0,
    "missing_verification": false,
    "missing_analysis": false,
    "is_transport_or_credit": false,
    "comments_count": 0,
    "date_formatted": "27/09/2019",
    "value_formatted": "R$ -10,00",
    "value_abs": 10,
    "cost_center_name_formatted": "Tarifas bancárias da conta corrente",
    "name": "ITAU UNIBANCO S.A.",
    "cpf_cnpj": "PJ: 60.701.190/0001-04",
    "pendencies": [

    ]
  },
  {
    "id": 2009,
    "date": "25/09/2019",
    "value": "-70.00",
    "cost_center_id": 13,
    "congressman_budget_id": 438,
    "object": "Suprimentos de informática",
    "to": "Adaptacabos 309 Comercio de Cabos e Comp. Eletr. Ltda",
    "entry_type_id": 5,
    "document_number": null,
    "provider_id": 267,
    "verified_at": "2019-11-28 17:13:05",
    "verified_by_id": 61,
    "analysed_at": "2019-12-20 15:53:08",
    "analysed_by_id": 75,
    "published_at": "2019-12-20 15:53:18",
    "published_by_id": 75,
    "created_at": "2019-09-30 20:30:40",
    "created_by_id": 61,
    "updated_at": "2019-12-20 15:53:18",
    "updated_by_id": 75,
    "cost_center_name": "Material de expediente e suprimentos de informática",
    "cost_center_code": "IV.b",
    "provider_name": "Adaptacabos 309 Comercio de Cabos e Comp. Eletr. Ltda",
    "provider_cpf_cnpj": "07.969.851/0001-96",
    "provider_type": "CNPJ",
    "entry_type_name": "Débito",
    "provider_is_blocked": false,
    "documents_count": 1,
    "missing_verification": false,
    "missing_analysis": false,
    "is_transport_or_credit": false,
    "comments_count": 0,
    "date_formatted": "25/09/2019",
    "value_formatted": "R$ -70,00",
    "value_abs": 70,
    "cost_center_name_formatted": "Material de expediente e suprimentos de informática",
    "name": "Adaptacabos 309 Comercio de Cabos e Comp. Eletr. Ltda",
    "cpf_cnpj": "CNPJ: 07.969.851/0001-96",
    "pendencies": [

    ]
  },
  {
    "id": 1695,
    "date": "24/09/2019",
    "value": "-2469.00",
    "cost_center_id": 21,
    "congressman_budget_id": 438,
    "object": "Locação de veículo",
    "to": "movida locação de veiculos s.a",
    "entry_type_id": 5,
    "document_number": null,
    "provider_id": 53,
    "verified_at": "2019-09-30 21:08:53",
    "verified_by_id": 61,
    "analysed_at": "2019-12-20 15:53:11",
    "analysed_by_id": 75,
    "published_at": "2019-12-20 15:53:20",
    "published_by_id": 75,
    "created_at": "2019-09-12 19:35:37",
    "created_by_id": 61,
    "updated_at": "2019-12-20 15:53:20",
    "updated_by_id": 75,
    "cost_center_name": "Locação ou fretamento de veículos automotores",
    "cost_center_code": "VI.a",
    "provider_name": "movida locação de veiculos s.a",
    "provider_cpf_cnpj": "07.976.147/0019-90",
    "provider_type": "CNPJ",
    "entry_type_name": "Débito",
    "provider_is_blocked": false,
    "documents_count": 1,
    "missing_verification": false,
    "missing_analysis": false,
    "is_transport_or_credit": false,
    "comments_count": 0,
    "date_formatted": "24/09/2019",
    "value_formatted": "R$ -2.469,00",
    "value_abs": 2469,
    "cost_center_name_formatted": "Locação ou fretamento de veículos automotores",
    "name": "movida locação de veiculos s.a",
    "cpf_cnpj": "CNPJ: 07.976.147/0019-90",
    "pendencies": [

    ]
  },
  {
    "id": 1696,
    "date": "24/09/2019",
    "value": "-3672.45",
    "cost_center_id": 21,
    "congressman_budget_id": 438,
    "object": "Locação de veículo",
    "to": "movida locação de veiculos s.a",
    "entry_type_id": 5,
    "document_number": null,
    "provider_id": 53,
    "verified_at": "2019-09-30 21:06:29",
    "verified_by_id": 61,
    "analysed_at": "2019-12-20 15:53:14",
    "analysed_by_id": 75,
    "published_at": "2019-12-20 15:53:49",
    "published_by_id": 75,
    "created_at": "2019-09-12 19:42:42",
    "created_by_id": 61,
    "updated_at": "2019-12-20 15:53:49",
    "updated_by_id": 75,
    "cost_center_name": "Locação ou fretamento de veículos automotores",
    "cost_center_code": "VI.a",
    "provider_name": "movida locação de veiculos s.a",
    "provider_cpf_cnpj": "07.976.147/0019-90",
    "provider_type": "CNPJ",
    "entry_type_name": "Débito",
    "provider_is_blocked": false,
    "documents_count": 1,
    "missing_verification": false,
    "missing_analysis": false,
    "is_transport_or_credit": false,
    "comments_count": 0,
    "date_formatted": "24/09/2019",
    "value_formatted": "R$ -3.672,45",
    "value_abs": 3672.45,
    "cost_center_name_formatted": "Locação ou fretamento de veículos automotores",
    "name": "movida locação de veiculos s.a",
    "cpf_cnpj": "CNPJ: 07.976.147/0019-90",
    "pendencies": [

    ]
  },
  {
    "id": 1810,
    "date": "18/09/2019",
    "value": "-777.05",
    "cost_center_id": 13,
    "congressman_budget_id": 438,
    "object": "Material de expediente.",
    "to": "Kalunga Comércio e Ind. Gráfica LTDA",
    "entry_type_id": 5,
    "document_number": null,
    "provider_id": 142,
    "verified_at": "2019-11-28 17:13:02",
    "verified_by_id": 61,
    "analysed_at": "2019-12-20 15:53:15",
    "analysed_by_id": 75,
    "published_at": "2019-12-20 15:53:52",
    "published_by_id": 75,
    "created_at": "2019-09-18 23:18:14",
    "created_by_id": 61,
    "updated_at": "2019-12-20 15:53:52",
    "updated_by_id": 75,
    "cost_center_name": "Material de expediente e suprimentos de informática",
    "cost_center_code": "IV.b",
    "provider_name": "Kalunga Comércio e Ind. Gráfica LTDA",
    "provider_cpf_cnpj": "43.283.811/0074-05",
    "provider_type": "CNPJ",
    "entry_type_name": "Débito",
    "provider_is_blocked": false,
    "documents_count": 1,
    "missing_verification": false,
    "missing_analysis": false,
    "is_transport_or_credit": false,
    "comments_count": 0,
    "date_formatted": "18/09/2019",
    "value_formatted": "R$ -777,05",
    "value_abs": 777.05,
    "cost_center_name_formatted": "Material de expediente e suprimentos de informática",
    "name": "Kalunga Comércio e Ind. Gráfica LTDA",
    "cpf_cnpj": "CNPJ: 43.283.811/0074-05",
    "pendencies": [

    ]
  },
  {
    "id": 2402,
    "date": "17/09/2019",
    "value": "-49132.41",
    "cost_center_id": 26,
    "congressman_budget_id": 438,
    "object": "Devolução de saldo acumulado.",
    "to": "Assembleia Legislativa do Estado do Rio de Janeiro",
    "entry_type_id": 3,
    "document_number": null,
    "provider_id": 1,
    "verified_at": "2019-10-15 19:43:05",
    "verified_by_id": 61,
    "analysed_at": "2019-12-20 15:53:25",
    "analysed_by_id": 75,
    "published_at": "2019-12-20 15:53:55",
    "published_by_id": 75,
    "created_at": "2019-10-15 19:42:51",
    "created_by_id": 61,
    "updated_at": "2019-12-20 15:53:55",
    "updated_by_id": 75,
    "cost_center_name": "Devolução de saldo",
    "cost_center_code": "4",
    "provider_name": "Assembleia Legislativa do Estado do Rio de Janeiro",
    "provider_cpf_cnpj": "30.449.862/0001-67",
    "provider_type": "PJ",
    "entry_type_name": "Transferência",
    "provider_is_blocked": false,
    "documents_count": 0,
    "missing_verification": false,
    "missing_analysis": false,
    "is_transport_or_credit": false,
    "comments_count": 0,
    "date_formatted": "17/09/2019",
    "value_formatted": "R$ -49.132,41",
    "value_abs": 49132.41,
    "cost_center_name_formatted": "Devolução de saldo",
    "name": "Assembleia Legislativa do Estado do Rio de Janeiro",
    "cpf_cnpj": "PJ: 30.449.862/0001-67",
    "pendencies": [

    ]
  },
  {
    "id": 1631,
    "date": "09/09/2019",
    "value": "-4000.00",
    "cost_center_id": 24,
    "congressman_budget_id": 438,
    "object": "Monitoramento de mídias sociais",
    "to": "Aplicanet Informática LTDA.",
    "entry_type_id": 4,
    "document_number": "AA000032",
    "provider_id": 236,
    "verified_at": "2019-09-12 19:31:29",
    "verified_by_id": 61,
    "analysed_at": "2019-12-20 15:53:33",
    "analysed_by_id": 75,
    "published_at": "2019-12-20 15:54:14",
    "published_by_id": 75,
    "created_at": "2019-09-09 19:43:11",
    "created_by_id": 61,
    "updated_at": "2019-12-20 15:54:14",
    "updated_by_id": 75,
    "cost_center_name": "Divulgação de sua atividade parlamentar, respeitadas as vedações de leis eleitorais",
    "cost_center_code": "VIII",
    "provider_name": "Aplicanet Informática LTDA.",
    "provider_cpf_cnpj": "08.083.926/0010-8",
    "provider_type": "0",
    "entry_type_name": "Cheque",
    "provider_is_blocked": false,
    "documents_count": 1,
    "missing_verification": false,
    "missing_analysis": false,
    "is_transport_or_credit": false,
    "comments_count": 0,
    "date_formatted": "09/09/2019",
    "value_formatted": "R$ -4.000,00",
    "value_abs": 4000,
    "cost_center_name_formatted": "Divulgação de sua atividade parlamentar, respeitadas as veda...",
    "name": "Aplicanet Informática LTDA.",
    "cpf_cnpj": "0: 08.083.926/0010-8",
    "pendencies": [

    ]
  },
  {
    "id": 1632,
    "date": "08/09/2019",
    "value": "-1312.43",
    "cost_center_id": 22,
    "congressman_budget_id": 438,
    "object": "Despesas com Locomoção",
    "to": "CGMP CENTRO DE GESTAO DE MEIOS DE PAGAMENTO LTDA",
    "entry_type_id": 4,
    "document_number": "AA000033",
    "provider_id": 11,
    "verified_at": "2020-11-09 20:59:53",
    "verified_by_id": 61,
    "analysed_at": "2020-11-09 23:15:37",
    "analysed_by_id": 75,
    "published_at": "2020-11-09 23:15:45",
    "published_by_id": 75,
    "created_at": "2019-09-09 19:53:44",
    "created_by_id": 61,
    "updated_at": "2020-11-09 23:15:45",
    "updated_by_id": 75,
    "cost_center_name": "Serviços de táxi, STIP, transportes públicos, pedágio e estacionamento",
    "cost_center_code": "VI.b",
    "provider_name": "CGMP CENTRO DE GESTAO DE MEIOS DE PAGAMENTO LTDA",
    "provider_cpf_cnpj": "04.088.208/0001-65",
    "provider_type": "CNPJ",
    "entry_type_name": "Cheque",
    "provider_is_blocked": false,
    "documents_count": 1,
    "missing_verification": false,
    "missing_analysis": false,
    "is_transport_or_credit": false,
    "comments_count": 0,
    "date_formatted": "08/09/2019",
    "value_formatted": "R$ -1.312,43",
    "value_abs": 1312.43,
    "cost_center_name_formatted": "Serviços de táxi, STIP, transportes públicos, pedágio e esta...",
    "name": "CGMP CENTRO DE GESTAO DE MEIOS DE PAGAMENTO LTDA",
    "cpf_cnpj": "CNPJ: 04.088.208/0001-65",
    "pendencies": [

    ]
  },
  {
    "id": 1608,
    "date": "06/09/2019",
    "value": "-306.66",
    "cost_center_id": 12,
    "congressman_budget_id": 438,
    "object": "Locação de equipamento",
    "to": "Hypercomputer Comercio e Serviços de Informatica LTDA",
    "entry_type_id": 4,
    "document_number": "AA000031",
    "provider_id": 162,
    "verified_at": "2020-05-04 16:15:22",
    "verified_by_id": 61,
    "analysed_at": "2020-05-04 16:24:03",
    "analysed_by_id": 75,
    "published_at": "2020-05-04 16:24:07",
    "published_by_id": 75,
    "created_at": "2019-09-06 22:57:05",
    "created_by_id": 61,
    "updated_at": "2020-05-04 16:24:07",
    "updated_by_id": 75,
    "cost_center_name": "Locação de móveis e equipamentos",
    "cost_center_code": "IV.a",
    "provider_name": "Hypercomputer Comercio e Serviços de Informatica LTDA",
    "provider_cpf_cnpj": "10.421.827/0001-22",
    "provider_type": "CNPJ",
    "entry_type_name": "Cheque",
    "provider_is_blocked": false,
    "documents_count": 1,
    "missing_verification": false,
    "missing_analysis": false,
    "is_transport_or_credit": false,
    "comments_count": 0,
    "date_formatted": "06/09/2019",
    "value_formatted": "R$ -306,66",
    "value_abs": 306.66,
    "cost_center_name_formatted": "Locação de móveis e equipamentos",
    "name": "Hypercomputer Comercio e Serviços de Informatica LTDA",
    "cpf_cnpj": "CNPJ: 10.421.827/0001-22",
    "pendencies": [

    ]
  },
  {
    "id": 1579,
    "date": "04/09/2019",
    "value": "-1139.16",
    "cost_center_id": 12,
    "congressman_budget_id": 438,
    "object": "Locação de equipamento",
    "to": "Hypercomputer Comercio e Serviços de Informatica LTDA",
    "entry_type_id": 4,
    "document_number": "AA000028",
    "provider_id": 162,
    "verified_at": "2020-05-04 16:15:53",
    "verified_by_id": 61,
    "analysed_at": "2020-05-04 16:24:05",
    "analysed_by_id": 75,
    "published_at": "2020-05-04 16:24:09",
    "published_by_id": 75,
    "created_at": "2019-09-05 00:40:56",
    "created_by_id": 61,
    "updated_at": "2020-05-04 16:24:09",
    "updated_by_id": 75,
    "cost_center_name": "Locação de móveis e equipamentos",
    "cost_center_code": "IV.a",
    "provider_name": "Hypercomputer Comercio e Serviços de Informatica LTDA",
    "provider_cpf_cnpj": "10.421.827/0001-22",
    "provider_type": "CNPJ",
    "entry_type_name": "Cheque",
    "provider_is_blocked": false,
    "documents_count": 1,
    "missing_verification": false,
    "missing_analysis": false,
    "is_transport_or_credit": false,
    "comments_count": 0,
    "date_formatted": "04/09/2019",
    "value_formatted": "R$ -1.139,16",
    "value_abs": 1139.16,
    "cost_center_name_formatted": "Locação de móveis e equipamentos",
    "name": "Hypercomputer Comercio e Serviços de Informatica LTDA",
    "cpf_cnpj": "CNPJ: 10.421.827/0001-22",
    "pendencies": [

    ]
  },
  {
    "id": 1578,
    "date": "01/09/2019",
    "value": "-650.00",
    "cost_center_id": 22,
    "congressman_budget_id": 438,
    "object": "Menezes Cortes",
    "to": "Terminal Garagem Menezes Côrtes S.A",
    "entry_type_id": 4,
    "document_number": "AA000027",
    "provider_id": 29,
    "verified_at": "2020-11-09 21:00:44",
    "verified_by_id": 61,
    "analysed_at": "2020-11-09 23:15:33",
    "analysed_by_id": 75,
    "published_at": "2020-11-09 23:15:42",
    "published_by_id": 75,
    "created_at": "2019-09-05 00:37:48",
    "created_by_id": 61,
    "updated_at": "2020-11-09 23:15:42",
    "updated_by_id": 75,
    "cost_center_name": "Serviços de táxi, STIP, transportes públicos, pedágio e estacionamento",
    "cost_center_code": "VI.b",
    "provider_name": "Terminal Garagem Menezes Côrtes S.A",
    "provider_cpf_cnpj": "02.664.042/0001-52",
    "provider_type": "CNPJ",
    "entry_type_name": "Cheque",
    "provider_is_blocked": false,
    "documents_count": 1,
    "missing_verification": false,
    "missing_analysis": false,
    "is_transport_or_credit": false,
    "comments_count": 0,
    "date_formatted": "01/09/2019",
    "value_formatted": "R$ -650,00",
    "value_abs": 650,
    "cost_center_name_formatted": "Serviços de táxi, STIP, transportes públicos, pedágio e esta...",
    "name": "Terminal Garagem Menezes Côrtes S.A",
    "cpf_cnpj": "CNPJ: 02.664.042/0001-52",
    "pendencies": [

    ]
  }
]